inference_perf/__init__.py
inference_perf/config.py
inference_perf/logger.py
inference_perf/main.py
inference_perf/analysis/__init__.py
inference_perf/analysis/analyze.py
inference_perf/apis/__init__.py
inference_perf/apis/base.py
inference_perf/apis/chat.py
inference_perf/apis/completion.py
inference_perf/client/filestorage/__init__.py
inference_perf/client/filestorage/base.py
inference_perf/client/filestorage/gcs.py
inference_perf/client/filestorage/local.py
inference_perf/client/filestorage/s3.py
inference_perf/client/metricsclient/__init__.py
inference_perf/client/metricsclient/base.py
inference_perf/client/metricsclient/mock_client.py
inference_perf/client/metricsclient/prometheus_client/__init__.py
inference_perf/client/metricsclient/prometheus_client/base.py
inference_perf/client/metricsclient/prometheus_client/google_managed_prometheus_client.py
inference_perf/client/modelserver/__init__.py
inference_perf/client/modelserver/base.py
inference_perf/client/modelserver/mock_client.py
inference_perf/client/modelserver/openai_client.py
inference_perf/client/modelserver/sglang_client.py
inference_perf/client/modelserver/tgi_client.py
inference_perf/client/modelserver/vllm_client.py
inference_perf/client/requestdatacollector/__init__.py
inference_perf/client/requestdatacollector/base.py
inference_perf/client/requestdatacollector/local.py
inference_perf/client/requestdatacollector/multiprocess.py
inference_perf/datagen/__init__.py
inference_perf/datagen/base.py
inference_perf/datagen/cnn_dailymail_datagen.py
inference_perf/datagen/hf_billsum_datagen.py
inference_perf/datagen/hf_sharegpt_datagen.py
inference_perf/datagen/infinity_instruct_datagen.py
inference_perf/datagen/mock_datagen.py
inference_perf/datagen/random_datagen.py
inference_perf/datagen/shared_prefix_datagen.py
inference_perf/datagen/synthetic_datagen.py
inference_perf/loadgen/__init__.py
inference_perf/loadgen/load_generator.py
inference_perf/loadgen/load_timer.py
inference_perf/reportgen/__init__.py
inference_perf-0.2.0.dist-info/licenses/LICENSE
inference_perf-0.2.0.dist-info/METADATA
inference_perf-0.2.0.dist-info/WHEEL
inference_perf-0.2.0.dist-info/entry_points.txt
inference_perf-0.2.0.dist-info/top_level.txt
inference_perf-0.2.0.dist-info/RECORD
