Metadata-Version: 2.4
Name: inference-perf
Version: 0.2.0
Summary: A GenAI inference performance benchmarking tool.
License: Apache-2.0
Requires-Python: >=3.12
License-File: LICENSE
Requires-Dist: aiohttp>=3.11.11
Requires-Dist: pydantic>=2.10.6
Requires-Dist: numpy>=2.2.2
Requires-Dist: datasets>=3.3.2
Requires-Dist: transformers>=4.50.2
Requires-Dist: google-cloud-storage>=3.1.0
Requires-Dist: pyyaml>=6.0.2
Requires-Dist: boto3>=1.39.0
Requires-Dist: uvloop>=0.21.0
Requires-Dist: tqdm>=4.67.1
Requires-Dist: types-tqdm>=4.67.0.20250809
Provides-Extra: analysis
Requires-Dist: matplotlib>=3.9.0; extra == "analysis"
Provides-Extra: dev
Requires-Dist: mypy>=1.14.1; extra == "dev"
Requires-Dist: ruff>=0.9.4; extra == "dev"
Requires-Dist: pre-commit>=4.1.0; extra == "dev"
Requires-Dist: pytest>=8.3.4; extra == "dev"
Requires-Dist: ipykernel>=6.29.5; extra == "dev"
Dynamic: license-file
